{
  "collectionName": "components_content_rich_texts",
  "info": {
    "displayName": "Rich Text",
    "description": "サニタイズ済み HTML",
    "icon": "align-left"
  },
  "attributes": {
    "body": {
      "type": "richtext",
      "required": true
    },
    "fontScale": {
      "type": "customField",
      "customField": "plugin::font-scale-range.scale",
      "default": null,
      "options": {
        "min": 0.7,
        "max": 1.8,
        "step": 0.05,
        "defaultScale": 1
      }
    }
  }
}
